notebookc/__init__.py
notebookc/notebookc.py
notebookc_krisnadi-0.0.2.dist-info/METADATA
notebookc_krisnadi-0.0.2.dist-info/WHEEL
notebookc_krisnadi-0.0.2.dist-info/top_level.txt
notebookc_krisnadi-0.0.2.dist-info/RECORD
